rtl/e203/perips/sirv_dma.v
/*                                                                      
Copyright 2018-2020 Nuclei System Technology, Inc.                
                                                                    
Licensed under the Apache License, Version 2.0 (the "License");         
you may not use this file except in compliance with the License.        
You may obtain a copy of the License at                                 
                                                                    
    http://www.apache.org/licenses/LICENSE-2.0                          
                                                                    
 Unless required by applicable law or agreed to in writing, software    
distributed under the License is distributed on an "AS IS" BASIS,       
WITHOUT WARRANTIES OR CONDITIONS OF ANY KIND, either express or implied.
See the License for the specific language governing permissions and     
limitations under the License.                                          
*/                                                                      
                                                                    
                                                                    
                                                                    
//=====================================================================
//
// Designer   : DMA Controller
//
// Description:
//  DMA controller with ICB bus interface for E203 SoC
//  Supports memory-to-memory data transfer
//
// ====================================================================

module sirv_dma #(
  parameter AW = 32,
  parameter DW = 32
)(
  input                clk,
  input                rst_n,

  // Configuration Interface (ICB Slave - from CPU)
  input                cfg_icb_cmd_valid,
  output               cfg_icb_cmd_ready,
  input  [AW-1:0]      cfg_icb_cmd_addr,
  input                cfg_icb_cmd_read,
  input  [DW-1:0]      cfg_icb_cmd_wdata,
  input  [DW/8-1:0]    cfg_icb_cmd_wmask,
  
  output               cfg_icb_rsp_valid,
  input                cfg_icb_rsp_ready,
  output [DW-1:0]      cfg_icb_rsp_rdata,
  output               cfg_icb_rsp_err,

  // Memory Interface (ICB Master - to memory)
  output               mem_icb_cmd_valid,
  input                mem_icb_cmd_ready,
  output [AW-1:0]      mem_icb_cmd_addr,
  output               mem_icb_cmd_read,
  output [DW-1:0]      mem_icb_cmd_wdata,
  output [DW/8-1:0]    mem_icb_cmd_wmask,
  
  input                mem_icb_rsp_valid,
  output               mem_icb_rsp_ready,
  input  [DW-1:0]      mem_icb_rsp_rdata,
  input                mem_icb_rsp_err,

  // Interrupt output
  output               dma_irq
);

  // Register offsets (5-bit address space: 32 bytes total)
  localparam REG_CTRL   = 5'h00;  // 0x00
  localparam REG_STATUS = 5'h04;  // 0x04
  localparam REG_SRC    = 5'h08;  // 0x08
  localparam REG_DST    = 5'h0C;  // 0x0C
  localparam REG_LEN    = 5'h10;  // 0x10

  // Control register bits
  localparam CTRL_ENABLE = 0;
  localparam CTRL_START  = 1;
  localparam CTRL_DIR    = 2;

  // Status register bits
  localparam STATUS_BUSY  = 0;
  localparam STATUS_DONE  = 1;
  localparam STATUS_ERROR = 2;

  // State machine states
  localparam STATE_IDLE      = 3'b000;
  localparam STATE_READ_REQ  = 3'b001;
  localparam STATE_READ_RSP  = 3'b010;
  localparam STATE_WRITE_REQ = 3'b011;
  localparam STATE_WRITE_RSP = 3'b100;
  localparam STATE_DONE      = 3'b101;

  // Registers
  reg [DW-1:0]    ctrl_reg;
  reg [DW-1:0]    status_reg;
  reg [AW-1:0]    src_reg;
  reg [AW-1:0]    dst_reg;
  reg [DW-1:0]    len_reg;
  
  // Internal signals
  reg [2:0]       state;
  reg [AW-1:0]    current_src;
  reg [AW-1:0]    current_dst;
  reg [DW-1:0]    remaining_len;
  reg [DW-1:0]    read_data_buf;
  
  wire            dma_enable;
  wire            dma_start;
  wire            dma_busy;
  wire            dma_done;
  wire            dma_error;
  
  assign dma_enable = ctrl_reg[CTRL_ENABLE];
  assign dma_start  = ctrl_reg[CTRL_START];
  assign dma_busy   = status_reg[STATUS_BUSY];
  assign dma_done   = status_reg[STATUS_DONE];
  assign dma_error  = status_reg[STATUS_ERROR];
  
  // Interrupt generation
  assign dma_irq = dma_done | dma_error;

  // Configuration interface handshake
  wire cfg_cmd_hsked = cfg_icb_cmd_valid & cfg_icb_cmd_ready;
  wire cfg_rsp_hsked = cfg_icb_rsp_valid & cfg_icb_rsp_ready;
  
  // Memory interface handshake
  wire mem_cmd_hsked = mem_icb_cmd_valid & mem_icb_cmd_ready;
  wire mem_rsp_hsked = mem_icb_rsp_valid & mem_icb_rsp_ready;

  // Configuration register access
  wire [4:0] cfg_addr_offset = cfg_icb_cmd_addr[4:0];
  wire cfg_sel_ctrl   = (cfg_addr_offset == REG_CTRL);
  wire cfg_sel_status = (cfg_addr_offset == REG_STATUS);
  wire cfg_sel_src    = (cfg_addr_offset == REG_SRC);
  wire cfg_sel_dst    = (cfg_addr_offset == REG_DST);
  wire cfg_sel_len    = (cfg_addr_offset == REG_LEN);

  // Configuration read data
  reg [DW-1:0] cfg_rdata;
  always @(*) begin
    case (cfg_addr_offset)
      REG_CTRL:   cfg_rdata = ctrl_reg;
      REG_STATUS: cfg_rdata = status_reg;
      REG_SRC:    cfg_rdata = {{(DW-AW){1'b0}}, src_reg};
      REG_DST:    cfg_rdata = {{(DW-AW){1'b0}}, dst_reg};
      REG_LEN:    cfg_rdata = len_reg;
      default:    cfg_rdata = {DW{1'b0}};
    endcase
  end

  // Configuration response
  reg cfg_rsp_valid_r;
  reg [DW-1:0] cfg_rsp_rdata_r;
  
  assign cfg_icb_cmd_ready = ~cfg_rsp_valid_r | cfg_rsp_hsked;
  assign cfg_icb_rsp_valid = cfg_rsp_valid_r;
  assign cfg_icb_rsp_rdata = cfg_rsp_rdata_r;
  assign cfg_icb_rsp_err   = 1'b0;

  always @(posedge clk or negedge rst_n) begin
    if (!rst_n) begin
      cfg_rsp_valid_r <= 1'b0;
      cfg_rsp_rdata_r <= {DW{1'b0}};
    end else if (cfg_cmd_hsked) begin
      cfg_rsp_valid_r <= 1'b1;
      cfg_rsp_rdata_r <= cfg_rdata;
    end else if (cfg_rsp_hsked) begin
      cfg_rsp_valid_r <= 1'b0;
    end
  end

  // Control register write
  wire ctrl_wr_ena = cfg_cmd_hsked & (~cfg_icb_cmd_read) & cfg_sel_ctrl;
  wire status_clr_done  = cfg_cmd_hsked & (~cfg_icb_cmd_read) & cfg_sel_status & cfg_icb_cmd_wdata[STATUS_DONE];
  wire status_clr_error = cfg_cmd_hsked & (~cfg_icb_cmd_read) & cfg_sel_status & cfg_icb_cmd_wdata[STATUS_ERROR];
  
  always @(posedge clk or negedge rst_n) begin
    if (!rst_n) begin
      ctrl_reg <= {DW{1'b0}};
    end else if (ctrl_wr_ena) begin
      ctrl_reg <= cfg_icb_cmd_wdata;
    end else if (state == STATE_DONE) begin
      // Clear start bit when done
      ctrl_reg[CTRL_START] <= 1'b0;
    end
  end

  // Status register
  always @(posedge clk or negedge rst_n) begin
    if (!rst_n) begin
      status_reg <= {DW{1'b0}};
    end else begin
      // Busy bit
      status_reg[STATUS_BUSY] <= (state != STATE_IDLE) && (state != STATE_DONE);
      
      // Done bit - set when transfer completes, cleared by writing 1
      if (state == STATE_DONE && (remaining_len == 0))
        status_reg[STATUS_DONE] <= 1'b1;
      else if (status_clr_done)
        status_reg[STATUS_DONE] <= 1'b0;
        
      // Error bit - set on error, cleared by writing 1
      if ((state == STATE_READ_RSP && mem_rsp_hsked && mem_icb_rsp_err) ||
          (state == STATE_WRITE_RSP && mem_rsp_hsked && mem_icb_rsp_err))
        status_reg[STATUS_ERROR] <= 1'b1;
      else if (status_clr_error)
        status_reg[STATUS_ERROR] <= 1'b0;
    end
  end

  // Source address register
  wire src_wr_ena = cfg_cmd_hsked & (~cfg_icb_cmd_read) & cfg_sel_src & ~dma_busy;
  always @(posedge clk or negedge rst_n) begin
    if (!rst_n)
      src_reg <= {AW{1'b0}};
    else if (src_wr_ena)
      src_reg <= cfg_icb_cmd_wdata[AW-1:0];
  end

  // Destination address register
  wire dst_wr_ena = cfg_cmd_hsked & (~cfg_icb_cmd_read) & cfg_sel_dst & ~dma_busy;
  always @(posedge clk or negedge rst_n) begin
    if (!rst_n)
      dst_reg <= {AW{1'b0}};
    else if (dst_wr_ena)
      dst_reg <= cfg_icb_cmd_wdata[AW-1:0];
  end

  // Length register
  wire len_wr_ena = cfg_cmd_hsked & (~cfg_icb_cmd_read) & cfg_sel_len & ~dma_busy;
  always @(posedge clk or negedge rst_n) begin
    if (!rst_n)
      len_reg <= {DW{1'b0}};
    else if (len_wr_ena)
      len_reg <= cfg_icb_cmd_wdata;
  end

  // DMA state machine
  always @(posedge clk or negedge rst_n) begin
    if (!rst_n) begin
      state <= STATE_IDLE;
      current_src <= {AW{1'b0}};
      current_dst <= {AW{1'b0}};
      remaining_len <= {DW{1'b0}};
      read_data_buf <= {DW{1'b0}};
    end else begin
      case (state)
        STATE_IDLE: begin
          if (dma_enable && dma_start && (len_reg > 0)) begin
            state <= STATE_READ_REQ;
            current_src <= src_reg;
            current_dst <= dst_reg;
            remaining_len <= len_reg;
          end
        end
        
        STATE_READ_REQ: begin
          if (mem_cmd_hsked) begin
            state <= STATE_READ_RSP;
          end
        end
        
        STATE_READ_RSP: begin
          if (mem_rsp_hsked) begin
            if (mem_icb_rsp_err) begin
              state <= STATE_DONE;
            end else begin
              read_data_buf <= mem_icb_rsp_rdata;
              state <= STATE_WRITE_REQ;
            end
          end
        end
        
        STATE_WRITE_REQ: begin
          if (mem_cmd_hsked) begin
            state <= STATE_WRITE_RSP;
          end
        end
        
        STATE_WRITE_RSP: begin
          if (mem_rsp_hsked) begin
            if (mem_icb_rsp_err) begin
              state <= STATE_DONE;
            end else begin
              // Increment by word size (assumes word-aligned transfers)
              current_src <= current_src + (DW/8);
              current_dst <= current_dst + (DW/8);
              remaining_len <= remaining_len - (DW/8);
              
              if (remaining_len <= (DW/8)) begin
                state <= STATE_DONE;
              end else begin
                state <= STATE_READ_REQ;
              end
            end
          end
        end
        
        STATE_DONE: begin
          state <= STATE_IDLE;
        end
        
        default: begin
          state <= STATE_IDLE;
        end
      endcase
    end
  end

  // Memory interface outputs
  assign mem_icb_cmd_valid = (state == STATE_READ_REQ) || (state == STATE_WRITE_REQ);
  assign mem_icb_cmd_addr  = (state == STATE_READ_REQ) ? current_src : current_dst;
  assign mem_icb_cmd_read  = (state == STATE_READ_REQ);
  assign mem_icb_cmd_wdata = read_data_buf;
  assign mem_icb_cmd_wmask = {(DW/8){1'b1}};
  
  assign mem_icb_rsp_ready = (state == STATE_READ_RSP) || (state == STATE_WRITE_RSP);

endmodule

tb/tb_dma.v
/*                                                                      
Copyright 2018-2020 Nuclei System Technology, Inc.                
                                                                    
Licensed under the Apache License, Version 2.0 (the "License");         
you may not use this file except in compliance with the License.        
You may obtain a copy of the License at                                 
                                                                    
    http://www.apache.org/licenses/LICENSE-2.0                          
                                                                    
 Unless required by applicable law or agreed to in writing, software    
distributed under the License is distributed on an "AS IS" BASIS,       
WITHOUT WARRANTIES OR CONDITIONS OF ANY KIND, either express or implied.
See the License for the specific language governing permissions and     
limitations under the License.                                          
*/                                                                      
                                                                    
                                                                    
                                                                    
//=====================================================================
//
// Designer   : DMA Testbench
//
// Description:
//  Testbench for DMA controller verification
//  Tests memory-to-memory data transfer
//
// ====================================================================

`timescale 1ns / 1ps

module tb_dma();

  // Memory model parameters
  localparam MEM_SIZE = 1024;       // Memory size in words
  localparam MEM_ADDR_WIDTH = 10;   // log2(MEM_SIZE)
  localparam WORD_SIZE = 4;         // Bytes per word (32-bit)

  // Clock and reset
  reg clk;
  reg rst_n;
  
  // DMA signals
  wire        cfg_icb_cmd_valid;
  wire        cfg_icb_cmd_ready;
  wire [31:0] cfg_icb_cmd_addr;
  wire        cfg_icb_cmd_read;
  wire [31:0] cfg_icb_cmd_wdata;
  wire [3:0]  cfg_icb_cmd_wmask;
  
  wire        cfg_icb_rsp_valid;
  wire        cfg_icb_rsp_ready;
  wire [31:0] cfg_icb_rsp_rdata;
  wire        cfg_icb_rsp_err;
  
  wire        mem_icb_cmd_valid;
  wire        mem_icb_cmd_ready;
  wire [31:0] mem_icb_cmd_addr;
  wire        mem_icb_cmd_read;
  wire [31:0] mem_icb_cmd_wdata;
  wire [3:0]  mem_icb_cmd_wmask;
  
  wire        mem_icb_rsp_valid;
  wire        mem_icb_rsp_ready;
  wire [31:0] mem_icb_rsp_rdata;
  wire        mem_icb_rsp_err;
  
  wire        dma_irq;
  
  // Test control signals
  reg         cfg_cmd_valid_r;
  reg [31:0]  cfg_cmd_addr_r;
  reg         cfg_cmd_read_r;
  reg [31:0]  cfg_cmd_wdata_r;
  reg [3:0]   cfg_cmd_wmask_r;
  reg         cfg_rsp_ready_r;
  
  assign cfg_icb_cmd_valid = cfg_cmd_valid_r;
  assign cfg_icb_cmd_addr  = cfg_cmd_addr_r;
  assign cfg_icb_cmd_read  = cfg_cmd_read_r;
  assign cfg_icb_cmd_wdata = cfg_cmd_wdata_r;
  assign cfg_icb_cmd_wmask = cfg_cmd_wmask_r;
  assign cfg_icb_rsp_ready = cfg_rsp_ready_r;

  // Simple memory model
  reg [31:0] memory [0:MEM_SIZE-1];
  reg        mem_rsp_valid_r;
  reg [31:0] mem_rsp_rdata_r;
  
  assign mem_icb_cmd_ready = 1'b1;  // Always ready
  assign mem_icb_rsp_valid = mem_rsp_valid_r;
  assign mem_icb_rsp_rdata = mem_rsp_rdata_r;
  assign mem_icb_rsp_err   = 1'b0;
  
  // Memory model logic
  always @(posedge clk or negedge rst_n) begin
    if (!rst_n) begin
      mem_rsp_valid_r <= 1'b0;
      mem_rsp_rdata_r <= 32'h0;
    end else begin
      mem_rsp_valid_r <= 1'b0;
      
      if (mem_icb_cmd_valid && mem_icb_cmd_ready) begin
        if (mem_icb_cmd_read) begin
          // Read operation: Use parameterized address width
          mem_rsp_rdata_r <= memory[mem_icb_cmd_addr[MEM_ADDR_WIDTH+1:2]];
          mem_rsp_valid_r <= 1'b1;
        end else begin
          // Write operation: Use parameterized address width
          memory[mem_icb_cmd_addr[MEM_ADDR_WIDTH+1:2]] <= mem_icb_cmd_wdata;
          mem_rsp_valid_r <= 1'b1;
        end
      end
    end
  end

  // DUT instantiation
  sirv_dma #(
    .AW(32),
    .DW(32)
  ) u_dma (
    .clk                (clk),
    .rst_n              (rst_n),
    
    .cfg_icb_cmd_valid  (cfg_icb_cmd_valid),
    .cfg_icb_cmd_ready  (cfg_icb_cmd_ready),
    .cfg_icb_cmd_addr   (cfg_icb_cmd_addr),
    .cfg_icb_cmd_read   (cfg_icb_cmd_read),
    .cfg_icb_cmd_wdata  (cfg_icb_cmd_wdata),
    .cfg_icb_cmd_wmask  (cfg_icb_cmd_wmask),
    
    .cfg_icb_rsp_valid  (cfg_icb_rsp_valid),
    .cfg_icb_rsp_ready  (cfg_icb_rsp_ready),
    .cfg_icb_rsp_rdata  (cfg_icb_rsp_rdata),
    .cfg_icb_rsp_err    (cfg_icb_rsp_err),
    
    .mem_icb_cmd_valid  (mem_icb_cmd_valid),
    .mem_icb_cmd_ready  (mem_icb_cmd_ready),
    .mem_icb_cmd_addr   (mem_icb_cmd_addr),
    .mem_icb_cmd_read   (mem_icb_cmd_read),
    .mem_icb_cmd_wdata  (mem_icb_cmd_wdata),
    .mem_icb_cmd_wmask  (mem_icb_cmd_wmask),
    
    .mem_icb_rsp_valid  (mem_icb_rsp_valid),
    .mem_icb_rsp_ready  (mem_icb_rsp_ready),
    .mem_icb_rsp_rdata  (mem_icb_rsp_rdata),
    .mem_icb_rsp_err    (mem_icb_rsp_err),
    
    .dma_irq            (dma_irq)
  );

  // Clock generation: 100MHz (10ns period)
  initial begin
    clk = 0;
    forever #5 clk = ~clk;
  end

  // Task: Write to DMA register
  task dma_write;
    input [31:0] addr;
    input [31:0] data;
    begin
      @(posedge clk);
      cfg_cmd_valid_r <= 1'b1;
      cfg_cmd_addr_r  <= addr;
      cfg_cmd_read_r  <= 1'b0;
      cfg_cmd_wdata_r <= data;
      cfg_cmd_wmask_r <= 4'hF;
      cfg_rsp_ready_r <= 1'b1;
      
      @(posedge clk);
      while (!cfg_icb_cmd_ready) @(posedge clk);
      
      cfg_cmd_valid_r <= 1'b0;
      
      while (!cfg_icb_rsp_valid) @(posedge clk);
      @(posedge clk);
      cfg_rsp_ready_r <= 1'b0;
    end
  endtask

  // Task: Read from DMA register
  task dma_read;
    input  [31:0] addr;
    output [31:0] data;
    begin
      @(posedge clk);
      cfg_cmd_valid_r <= 1'b1;
      cfg_cmd_addr_r  <= addr;
      cfg_cmd_read_r  <= 1'b1;
      cfg_cmd_wdata_r <= 32'h0;
      cfg_cmd_wmask_r <= 4'h0;
      cfg_rsp_ready_r <= 1'b1;
      
      @(posedge clk);
      while (!cfg_icb_cmd_ready) @(posedge clk);
      
      cfg_cmd_valid_r <= 1'b0;
      
      while (!cfg_icb_rsp_valid) @(posedge clk);
      data = cfg_icb_rsp_rdata;
      @(posedge clk);
      cfg_rsp_ready_r <= 1'b0;
    end
  endtask

  // Test stimulus
  integer i;
  reg [31:0] read_data;
  reg [31:0] expected_data;
  integer errors;
  
  initial begin
    // Initialize signals
    rst_n = 0;
    cfg_cmd_valid_r = 0;
    cfg_cmd_addr_r  = 0;
    cfg_cmd_read_r  = 0;
    cfg_cmd_wdata_r = 0;
    cfg_cmd_wmask_r = 0;
    cfg_rsp_ready_r = 0;
    errors = 0;
    
    // Initialize memory with test data
    for (i = 0; i < 1024; i = i + 1) begin
      memory[i] = 32'h0;
    end
    
    // Source data: addresses 0x00-0x3F (16 words)
    for (i = 0; i < 16; i = i + 1) begin
      memory[i] = 32'hA5A5_0000 + i;
    end
    
    // Reset
    #100;
    rst_n = 1;
    #50;
    
    $display("===================================");
    $display("DMA Controller Testbench Starting");
    $display("===================================");
    
    // Test 1: Register read/write
    $display("\nTest 1: Register Access");
    dma_write(32'h00, 32'h00000001);  // Write CTRL
    dma_read(32'h00, read_data);
    if (read_data == 32'h00000001) begin
      $display("  CTRL register write/read: PASS");
    end else begin
      $display("  CTRL register write/read: FAIL (expected 0x00000001, got 0x%08h)", read_data);
      errors = errors + 1;
    end
    
    // Test 2: Memory-to-memory transfer
    $display("\nTest 2: Memory-to-Memory DMA Transfer");
    $display("  Source address: 0x0000");
    $display("  Destination address: 0x0100");
    $display("  Transfer length: 64 bytes (16 words)");
    
    // Configure DMA
    dma_write(32'h08, 32'h00000000);  // SRC address = 0x0000
    dma_write(32'h0C, 32'h00000100);  // DST address = 0x0100
    dma_write(32'h10, 32'h00000040);  // LEN = 64 bytes
    dma_write(32'h00, 32'h00000003);  // CTRL: enable + start
    
    // Wait for completion
    $display("  Waiting for DMA transfer...");
    read_data = 0;
    while ((read_data & 32'h00000002) == 0) begin
      #100;
      dma_read(32'h04, read_data);  // Read STATUS
    end
    
    if ((read_data & 32'h00000004) != 0) begin
      $display("  DMA transfer: FAIL (error bit set)");
      errors = errors + 1;
    end else begin
      $display("  DMA transfer completed");
      
      // Verify transferred data
      $display("  Verifying transferred data...");
      for (i = 0; i < 16; i = i + 1) begin
        expected_data = 32'hA5A5_0000 + i;
        if (memory[64 + i] != expected_data) begin
          $display("    Mismatch at word %0d: expected 0x%08h, got 0x%08h", 
                   i, expected_data, memory[64 + i]);
          errors = errors + 1;
        end
      end
      
      if (errors == 0) begin
        $display("  Data verification: PASS");
      end else begin
        $display("  Data verification: FAIL (%0d errors)", errors);
      end
    end
    
    // Test 3: Interrupt verification
    $display("\nTest 3: Interrupt Verification");
    if (dma_irq) begin
      $display("  Interrupt signal asserted: PASS");
    end else begin
      $display("  Interrupt signal not asserted: FAIL");
      errors = errors + 1;
    end
    
    // Clear done status
    dma_write(32'h04, 32'h00000002);  // Clear DONE bit
    #50;
    
    if (!dma_irq) begin
      $display("  Interrupt signal cleared: PASS");
    end else begin
      $display("  Interrupt signal not cleared: FAIL");
      errors = errors + 1;
    end
    
    // Final result
    $display("\n===================================");
    if (errors == 0) begin
      $display("All tests PASSED!");
    end else begin
      $display("Tests FAILED with %0d errors", errors);
    end
    $display("===================================\n");
    
    #100;
    $finish;
  end

  // VCD dump for waveform viewing
  initial begin
    $dumpfile("tb_dma.vcd");
    $dumpvars(0, tb_dma);
  end

  // Timeout watchdog
  initial begin
    #100000;
    $display("ERROR: Simulation timeout!");
    $finish;
  end

endmodule

tb_dma.vcd
$date
	Fri Dec 12 14:04:20 2025
$end
$version
	Icarus Verilog
$end
$timescale
	1ps
$end
$scope module tb_dma $end
$var wire 32 ! cfg_icb_cmd_addr [31:0] $end
$var wire 1 " cfg_icb_cmd_read $end
$var wire 1 # cfg_icb_cmd_valid $end
$var wire 32 $ cfg_icb_cmd_wdata [31:0] $end
$var wire 4 % cfg_icb_cmd_wmask [3:0] $end
$var wire 1 & cfg_icb_rsp_err $end
$var wire 1 ' mem_icb_cmd_ready $end
$var wire 4 ( mem_icb_cmd_wmask [3:0] $end
$var wire 1 ) mem_icb_rsp_err $end
$var wire 32 * mem_icb_rsp_rdata [31:0] $end
$var wire 1 + mem_icb_rsp_valid $end
$var wire 1 , mem_icb_rsp_ready $end
$var wire 32 - mem_icb_cmd_wdata [31:0] $end
$var wire 1 . mem_icb_cmd_valid $end
$var wire 1 / mem_icb_cmd_read $end
$var wire 32 0 mem_icb_cmd_addr [31:0] $end
$var wire 1 1 dma_irq $end
$var wire 1 2 cfg_icb_rsp_valid $end
$var wire 1 3 cfg_icb_rsp_ready $end
$var wire 32 4 cfg_icb_rsp_rdata [31:0] $end
$var wire 1 5 cfg_icb_cmd_ready $end
$var parameter 32 6 MEM_ADDR_WIDTH $end
$var parameter 32 7 MEM_SIZE $end
$var parameter 32 8 WORD_SIZE $end
$var reg 32 9 cfg_cmd_addr_r [31:0] $end
$var reg 1 " cfg_cmd_read_r $end
$var reg 1 # cfg_cmd_valid_r $end
$var reg 32 : cfg_cmd_wdata_r [31:0] $end
$var reg 4 ; cfg_cmd_wmask_r [3:0] $end
$var reg 1 3 cfg_rsp_ready_r $end
$var reg 1 < clk $end
$var reg 32 = expected_data [31:0] $end
$var reg 32 > mem_rsp_rdata_r [31:0] $end
$var reg 1 + mem_rsp_valid_r $end
$var reg 32 ? read_data [31:0] $end
$var reg 1 @ rst_n $end
$var integer 32 A errors [31:0] $end
$var integer 32 B i [31:0] $end
$scope module u_dma $end
$var wire 1 C cfg_cmd_hsked $end
$var wire 32 D cfg_icb_cmd_addr [31:0] $end
$var wire 1 " cfg_icb_cmd_read $end
$var wire 1 5 cfg_icb_cmd_ready $end
$var wire 1 # cfg_icb_cmd_valid $end
$var wire 32 E cfg_icb_cmd_wdata [31:0] $end
$var wire 4 F cfg_icb_cmd_wmask [3:0] $end
$var wire 1 & cfg_icb_rsp_err $end
$var wire 32 G cfg_icb_rsp_rdata [31:0] $end
$var wire 1 3 cfg_icb_rsp_ready $end
$var wire 1 2 cfg_icb_rsp_valid $end
$var wire 1 H cfg_rsp_hsked $end
$var wire 1 < clk $end
$var wire 1 I ctrl_wr_ena $end
$var wire 1 1 dma_irq $end
$var wire 1 J dst_wr_ena $end
$var wire 1 K len_wr_ena $end
$var wire 1 L mem_cmd_hsked $end
$var wire 1 ' mem_icb_cmd_ready $end
$var wire 1 . mem_icb_cmd_valid $end
$var wire 32 M mem_icb_cmd_wdata [31:0] $end
$var wire 4 N mem_icb_cmd_wmask [3:0] $end
$var wire 1 ) mem_icb_rsp_err $end
$var wire 32 O mem_icb_rsp_rdata [31:0] $end
$var wire 1 , mem_icb_rsp_ready $end
$var wire 1 + mem_icb_rsp_valid $end
$var wire 1 P mem_rsp_hsked $end
$var wire 1 @ rst_n $end
$var wire 1 Q src_wr_ena $end
$var wire 1 R status_clr_done $end
$var wire 1 S status_clr_error $end
$var wire 1 / mem_icb_cmd_read $end
$var wire 32 T mem_icb_cmd_addr [31:0] $end
$var wire 1 U dma_start $end
$var wire 1 V dma_error $end
$var wire 1 W dma_enable $end
$var wire 1 X dma_done $end
$var wire 1 Y dma_busy $end
$var wire 1 Z cfg_sel_status $end
$var wire 1 [ cfg_sel_src $end
$var wire 1 \ cfg_sel_len $end
$var wire 1 ] cfg_sel_dst $end
$var wire 1 ^ cfg_sel_ctrl $end
$var wire 5 _ cfg_addr_offset [4:0] $end
$var parameter 32 ` AW $end
$var parameter 32 a CTRL_DIR $end
$var parameter 32 b CTRL_ENABLE $end
$var parameter 32 c CTRL_START $end
$var parameter 32 d DW $end
$var parameter 5 e REG_CTRL $end
$var parameter 5 f REG_DST $end
$var parameter 5 g REG_LEN $end
$var parameter 5 h REG_SRC $end
$var parameter 5 i REG_STATUS $end
$var parameter 3 j STATE_DONE $end
$var parameter 3 k STATE_IDLE $end
$var parameter 3 l STATE_READ_REQ $end
$var parameter 3 m STATE_READ_RSP $end
$var parameter 3 n STATE_WRITE_REQ $end
$var parameter 3 o STATE_WRITE_RSP $end
$var parameter 32 p STATUS_BUSY $end
$var parameter 32 q STATUS_DONE $end
$var parameter 32 r STATUS_ERROR $end
$var reg 32 s cfg_rdata [31:0] $end
$var reg 32 t cfg_rsp_rdata_r [31:0] $end
$var reg 1 u cfg_rsp_valid_r $end
$var reg 32 v ctrl_reg [31:0] $end
$var reg 32 w current_dst [31:0] $end
$var reg 32 x current_src [31:0] $end
$var reg 32 y dst_reg [31:0] $end
$var reg 32 z len_reg [31:0] $end
$var reg 32 { read_data_buf [31:0] $end
$var reg 32 | remaining_len [31:0] $end
$var reg 32 } src_reg [31:0] $end
$var reg 3 ~ state [2:0] $end
$var reg 32 !" status_reg [31:0] $end
$upscope $end
$scope task dma_read $end
$var reg 32 "" addr [31:0] $end
$var reg 32 #" data [31:0] $end
$upscope $end
$scope task dma_write $end
$var reg 32 $" addr [31:0] $end
$var reg 32 %" data [31:0] $end
$upscope $end
$upscope $end
$enddefinitions $end
$comment Show the parameter values. $end
$dumpall
b10 r
b1 q
b0 p
b100 o
b11 n
b10 m
b1 l
b0 k
b101 j
b100 i
b1000 h
b10000 g
b1100 f
b0 e
b100000 d
b1 c
b0 b
b10 a
b100000 `
b100 8
b10000000000 7
b1010 6
$end
#0
$dumpvars
bx %"
bx $"
bx #"
bx ""
b0 !"
b0 ~
b0 }
b0 |
b0 {
b0 z
b0 y
b0 x
b0 w
b0 v
0u
b0 t
b0 s
b0 _
1^
0]
0\
0[
0Z
0Y
0X
0W
0V
0U
b0 T
0S
0R
0Q
0P
b0 O
b1111 N
b0 M
0L
0K
0J
0I
0H
b0 G
b0 F
b0 E
b0 D
0C
b10000 B
b0 A
0@
bx ?
b0 >
bx =
0<
b0 ;
b0 :
b0 9
15
b0 4
03
02
01
b0 0
0/
0.
b0 -
0,
0+
b0 *
0)
b1111 (
1'
0&
b0 %
b0 $
0#
0"
b0 !
$end
#5000
1<
#10000
0<
#15000
1<
#20000
0<
#25000
1<
#30000
0<
#35000
1<
#40000
0<
#45000
1<
#50000
0<
#55000
1<
#60000
0<
#65000
1<
#70000
0<
#75000
1<
#80000
0<
#85000
1<
#90000
0<
#95000
1<
#100000
0<
1@
#105000
1<
#110000
0<
#115000
1<
#120000
0<
#125000
1<
#130000
0<
#135000
1<
#140000
0<
#145000
1<
#150000
0<
b1 %"
b0 $"
#155000
1I
1C
13
b1111 %
b1111 F
b1111 ;
b1 $
b1 :
b1 E
1#
1<
#160000
0<
#165000
0I
b1 s
1W
1H
0C
b1 v
12
1u
0#
1<
#170000
0<
#175000
0H
02
0u
1<
#180000
0<
#185000
03
b0 ""
1<
#190000
0<
#195000
1C
13
b0 %
b0 F
b0 ;
b0 $
b0 :
b0 E
1"
1#
1<
#200000
0<
#205000
1H
0C
b1 4
b1 G
b1 t
12
1u
0#
1<
#210000
0<
#215000
0H
02
0u
b1 #"
1<
#220000
0<
#225000
03
b0 %"
b1000 $"
b1 ?
1<
#230000
0<
#235000
1Q
b0 s
0^
1[
b1000 _
1C
13
b1111 %
b1111 F
b1111 ;
0"
b1000 !
b1000 9
b1000 D
1#
1<
#240000
0<
#245000
0Q
1H
0C
b0 4
b0 G
b0 t
12
1u
0#
1<
#250000
0<
#255000
0H
02
0u
1<
#260000
0<
#265000
03
b100000000 %"
b1100 $"
1<
#270000
0<
#275000
1J
0[
1]
b1100 _
1C
13
b100000000 $
b100000000 :
b100000000 E
b1100 !
b1100 9
b1100 D
1#
1<
#280000
0<
#285000
0J
b100000000 s
1H
0C
b100000000 y
12
1u
0#
1<
#290000
0<
#295000
0H
02
0u
1<
#300000
0<
#305000
03
b1000000 %"
b10000 $"
1<
#310000
0<
#315000
1K
b0 s
0]
1\
b10000 _
1C
13
b1000000 $
b1000000 :
b1000000 E
b10000 !
b10000 9
b10000 D
1#
1<
#320000
0<
#325000
0K
b1000000 s
1H
0C
b1000000 z
12
1u
0#
1<
#330000
0<
#335000
0H
02
0u
1<
#340000
0<
#345000
03
b11 %"
b0 $"
1<
#350000
0<
#355000
1I
b1 s
1^
0\
b0 _
1C
13
b11 $
b11 :
b11 E
b0 !
b0 9
b0 D
1#
1<
#360000
0<
#365000
0I
b11 s
1U
1H
0C
b11 v
b1 4
b1 G
b1 t
12
1u
0#
1<
#370000
0<
#375000
1L
0H
1.
02
0u
b1000000 |
b100000000 w
1/
b1 ~
1<
#380000
0<
#385000
0L
1P
0.
b100000000 0
b100000000 T
1,
1Y
1+
b10100101101001010000000000000000 *
b10100101101001010000000000000000 O
b10100101101001010000000000000000 >
0/
b10 ~
b1 !"
03
b0 ?
1<
#390000
0<
#395000
1L
1.
0,
0P
b11 ~
b10100101101001010000000000000000 -
b10100101101001010000000000000000 M
b10100101101001010000000000000000 {
0+
1<
#400000
0<
#405000
0L
1P
0.
1,
1+
b100 ~
1<
#410000
0<
#415000
1L
1.
0,
b100 0
b100 T
0P
1/
b1 ~
b111100 |
b100000100 w
b100 x
0+
1<
#420000
0<
#425000
0L
1P
0.
b100000100 0
b100000100 T
1,
1+
b10100101101001010000000000000001 *
b10100101101001010000000000000001 O
b10100101101001010000000000000001 >
0/
b10 ~
1<
#430000
0<
#435000
1L
1.
0,
0P
b11 ~
b10100101101001010000000000000001 -
b10100101101001010000000000000001 M
b10100101101001010000000000000001 {
0+
1<
#440000
0<
#445000
0L
1P
0.
1,
1+
b100 ~
1<
#450000
0<
